script_runner/__init__.py
script_runner/app.py
script_runner/approval_policy.py
script_runner/approval_store.py
script_runner/audit_log.py
script_runner/auth.py
script_runner/config.py
script_runner/config.schema.json
script_runner/context.py
script_runner/decorators.py
script_runner/function.py
script_runner/function_parameter.py
script_runner/py.typed
script_runner/testutils.py
script_runner/utils.py
script_runner/blueprints/__init__.py
script_runner/blueprints/base_app_bp.py
script_runner/blueprints/main_bp.py
script_runner/blueprints/region_bp.py
script_runner/blueprints/static_routes_bp.py
script_runner/frontend/dist/index.html
script_runner/frontend/dist/jq.wasm
script_runner/frontend/dist/assets/index-C9mhDjgR.js
script_runner/frontend/dist/assets/index-DvJnrQOE.css
sentry_script_runner-1.0.1.dist-info/licenses/LICENSE
sentry_script_runner-1.0.1.dist-info/METADATA
sentry_script_runner-1.0.1.dist-info/WHEEL
sentry_script_runner-1.0.1.dist-info/entry_points.txt
sentry_script_runner-1.0.1.dist-info/top_level.txt
sentry_script_runner-1.0.1.dist-info/RECORD
